setup.py
torngas/__init__.py
torngas/application.py
torngas/exception.py
torngas/global_settings.py
torngas/handler.py
torngas/settings_manager.py
torngas/signal.py
torngas/storage.py
torngas/urlhelper.py
torngas/utils.py
torngas/webserver.py
torngas.egg-info/PKG-INFO
torngas.egg-info/SOURCES.txt
torngas.egg-info/dependency_links.txt
torngas.egg-info/requires.txt
torngas.egg-info/top_level.txt
torngas/cache/__init__.py
torngas/cache/lru_cache.py
torngas/cache/backends/__init__.py
torngas/cache/backends/base.py
torngas/cache/backends/dummy.py
torngas/cache/backends/localcache.py
torngas/cache/backends/memcached.py
torngas/cache/backends/rediscache.py
torngas/db/__init__.py
torngas/db/basedb.py
torngas/db/dbalchemy.py
torngas/decorators/__init__.py
torngas/decorators/async_execute.py
torngas/decorators/whitelist.py
torngas/dispatch/__init__.py
torngas/dispatch/dispatcher.py
torngas/dispatch/weakref_backports.py
torngas/httpmodule/__init__.py
torngas/httpmodule/httpmodule.py
torngas/logger/__init__.py
torngas/logger/client.py
torngas/logger/loggers.py
torngas/middleware/__init__.py
torngas/middleware/accesslog.py
torngas/middleware/dbalchemy.py
torngas/middleware/manager.py
torngas/middleware/session.py
torngas/middleware/signal.py
torngas/mixins/__init__.py
torngas/mixins/exception.py
torngas/mixins/flash_message.py
torngas/mixins/miiddleware.py
torngas/resource/exception.html
torngas/template/__init__.py
torngas/template/jinja2_loader.py
torngas/template/mako_loader.py