Metadata-Version: 1.1
Name: torngas
Version: 1.8.1
Summary: torngas based on tornado
Home-page: https://github.com/mqingyn/torngas
Author: mqingyn
Author-email: mqingyn@gmail.com
License: BSD
Keywords: python torngas django tornado
Platform: UNKNOWN
Classifier: Development Status :: 4 - Beta
Classifier: License :: OSI Approved :: BSD License
Classifier: Programming Language :: Python :: 2
Classifier: Programming Language :: Python :: 2.6
Classifier: Programming Language :: Python :: 2.7
Classifier: Programming Language :: Python :: Implementation :: CPython
Classifier: Programming Language :: Python :: Implementation :: PyPy
Requires: tornado
Requires: futures
